nlpipy/__init__.py
nlpipy/components/__init__.py
nlpipy-0.1.0.dist-info/WHEEL
nlpipy-0.1.0.dist-info/METADATA
nlpipy-0.1.0.dist-info/license_files/LICENSE
nlpipy-0.1.0.dist-info/RECORD
