Metadata-Version: 2.1
Name: nlpipy
Version: 0.1.0
License: MIT
Author-email: wangmengdi <790990241@qq.com>
Requires-Python: >=3.9
Requires-Dist: spacy==3.4.1
